odoo/addons/jsonifier_stored/README.rst
odoo/addons/jsonifier_stored/__init__.py
odoo/addons/jsonifier_stored/__manifest__.py
odoo/addons/jsonifier_stored/hooks.py
odoo/addons/jsonifier_stored/data/ir_cron.xml
odoo/addons/jsonifier_stored/data/queue_job.xml
odoo/addons/jsonifier_stored/i18n/es.po
odoo/addons/jsonifier_stored/i18n/it.po
odoo/addons/jsonifier_stored/i18n/jsonifier_stored.pot
odoo/addons/jsonifier_stored/models/__init__.py
odoo/addons/jsonifier_stored/models/jsonifier_stored_mixin.py
odoo/addons/jsonifier_stored/readme/CONTRIBUTORS.rst
odoo/addons/jsonifier_stored/readme/DESCRIPTION.rst
odoo/addons/jsonifier_stored/readme/ROADMAP.rst
odoo/addons/jsonifier_stored/readme/USAGE.rst
odoo/addons/jsonifier_stored/static/description/icon.png
odoo/addons/jsonifier_stored/static/description/index.html
odoo/addons/jsonifier_stored/tests/__init__.py
odoo/addons/jsonifier_stored/tests/common.py
odoo/addons/jsonifier_stored/tests/fake_models.py
odoo/addons/jsonifier_stored/tests/test_cron.py
odoo/addons/jsonifier_stored/tests/test_multi_lang.py
odoo/addons/jsonifier_stored/tests/test_single_lang.py
odoo/addons/jsonifier_stored/tests/fixtures/ir_exports_test.xml
odoo14_addon_jsonifier_stored-14.0.1.0.1.dev11.dist-info/METADATA
odoo14_addon_jsonifier_stored-14.0.1.0.1.dev11.dist-info/WHEEL
odoo14_addon_jsonifier_stored-14.0.1.0.1.dev11.dist-info/top_level.txt
odoo14_addon_jsonifier_stored-14.0.1.0.1.dev11.dist-info/RECORD
